PyMilitary/.DS_Store
PyMilitary/__init__.py
PyMilitary/messages.py
PyMilitary/.ipynb_checkpoints/Untitled-checkpoint.ipynb
PyMilitary/dataset/.DS_Store
PyMilitary/dataset/__init__.py
PyMilitary/dataset/type1.py
pymilitary-0.0.3.dist-info/METADATA
pymilitary-0.0.3.dist-info/WHEEL
pymilitary-0.0.3.dist-info/RECORD
