Metadata-Version: 2.1
Name: PyMilitary
Version: 0.0.3
Summary: Open and read military message
Project-URL: Homepage, https://github.com/pypa/sampleproject
Project-URL: Bug Tracker, https://github.com/pypa/sampleproject/issues
Author-email: Minghao <shiminghao.work@gmail.com>
Classifier: Operating System :: OS Independent
Classifier: Programming Language :: Python :: 3
Requires-Python: >=3.7
